favorite_list_pkg/__init__.py
favorite_list_pkg/favorite_list.py
favorite_list_pkg_olajide1-0.0.1.dist-info/LICENSE
favorite_list_pkg_olajide1-0.0.1.dist-info/METADATA
favorite_list_pkg_olajide1-0.0.1.dist-info/WHEEL
favorite_list_pkg_olajide1-0.0.1.dist-info/top_level.txt
favorite_list_pkg_olajide1-0.0.1.dist-info/RECORD
