Metadata-Version: 2.1
Name: favorite_list_pkg_olajide1
Version: 0.0.1
Summary: A small package to import favorite list
Home-page: https://github.com/pypa/sampleproject
Author: Olajide Olawuyi
Author-email: jideolawuyi1@gmail.com
Classifier: Programming Language :: Python :: 3
Classifier: License :: OSI Approved :: MIT License
Classifier: Operating System :: OS Independent
Requires-Python: >=3.6
License-File: LICENSE
